{"errors":[],"warnings":[],"namedChunkGroups":{"app":{"chunks":[3,0],"assets":["webpack-runtime-35ea439037d3f3b6bcff.js","webpack-runtime-35ea439037d3f3b6bcff.js.map","app-7601d9e03d3b3e9c0604.js","app-7601d9e03d3b3e9c0604.js.map"],"children":{},"childAssets":{}},"component---src-pages-index-js":{"chunks":[2,4,1],"assets":["styles.e1819fd37571530d7105.css","styles-5bfd12723995bfd416fc.js","styles-5bfd12723995bfd416fc.js.map","4-77c46a40f15bd82400ca.js","4-77c46a40f15bd82400ca.js.map","component---src-pages-index-js-b77cb47e1be5613db17c.js","component---src-pages-index-js-b77cb47e1be5613db17c.js.map"],"children":{},"childAssets":{}}},"assetsByChunkName":{"app":["webpack-runtime-35ea439037d3f3b6bcff.js","app-7601d9e03d3b3e9c0604.js"],"component---src-pages-index-js":["styles.e1819fd37571530d7105.css","styles-5bfd12723995bfd416fc.js","4-77c46a40f15bd82400ca.js","component---src-pages-index-js-b77cb47e1be5613db17c.js"]}}